twick
